mass_driver/__init__.py
mass_driver/activity_run.py
mass_driver/cli.py
mass_driver/commands.py
mass_driver/discovery.py
mass_driver/drivers/__init__.py
mass_driver/drivers/bricks.py
mass_driver/drivers/counter.py
mass_driver/drivers/deleter.py
mass_driver/drivers/shell.py
mass_driver/drivers/stamper.py
mass_driver/forge_run.py
mass_driver/forges/__init__.py
mass_driver/forges/dummy.py
mass_driver/forges/github.py
mass_driver/git.py
mass_driver/models/__init__.py
mass_driver/models/activity.py
mass_driver/models/forge.py
mass_driver/models/migration.py
mass_driver/models/patchdriver.py
mass_driver/models/repository.py
mass_driver/models/scan.py
mass_driver/process_repo.py
mass_driver/py.typed
mass_driver/review_run.py
mass_driver/scanners/__init__.py
mass_driver/scanners/basic_scanners.py
mass_driver/sources/__init__.py
mass_driver/sources/github_source.py
mass_driver/sources/simple.py
mass_driver/summarize.py
mass_driver/tests/__init__.py
mass_driver/tests/data/activity.toml
mass_driver/tests/data/sample_repo/README.md
mass_driver/tests/data/sample_repo/counter.txt
mass_driver/tests/fixtures.py
mass_driver/tests/sample_result.py
mass_driver/tests/test_activity.py
mass_driver/tests/test_counterdriver/count_to_1/input.txt
mass_driver/tests/test_counterdriver/count_to_1/migration.toml
mass_driver/tests/test_counterdriver/count_to_1/outcome.txt
mass_driver/tests/test_counterdriver/count_to_1/output.txt
mass_driver/tests/test_counterdriver/count_to_2/input.txt
mass_driver/tests/test_counterdriver/count_to_2/migration.toml
mass_driver/tests/test_counterdriver/count_to_2/output.txt
mass_driver/tests/test_counterdriver.py
mass_driver/tests/test_plugins_listing.py
mass_driver/tests/test_scanner/dockerfile/Dockerfile
mass_driver/tests/test_scanner/dockerfile/activity.toml
mass_driver/tests/test_scanner/dockerfile/scan_results.json
mass_driver/tests/test_scanner/multiple-dockerfiles/Dockerfile
mass_driver/tests/test_scanner/multiple-dockerfiles/activity.toml
mass_driver-0.20.0.dist-info/COPYING
mass_driver-0.20.0.dist-info/METADATA
mass_driver-0.20.0.dist-info/WHEEL
mass_driver-0.20.0.dist-info/entry_points.txt
mass_driver-0.20.0.dist-info/RECORD
