Metadata-Version: 2.1
Name: mass_driver
Version: 0.20.0
Summary: Send bulk repo change requests
Home-page: https://github.com/OverkillGuy/mass-driver
License: GPL-3.0-or-later
Keywords: repo-automation
Author: Jb Doyon
Author-email: jb@jiby.tech
Requires-Python: >=3.11,<4.0
Classifier: Development Status :: 3 - Alpha
Classifier: License :: OSI Approved :: GNU General Public License v3 or later (GPLv3+)
Classifier: Programming Language :: Python :: 3
Classifier: Programming Language :: Python :: 3.11
Classifier: Programming Language :: Python :: 3.12
Classifier: Topic :: Software Development :: Code Generators
Requires-Dist: GitPython
Requires-Dist: PyGithub (==2.1.1)
Requires-Dist: pydantic (==1.*)
Project-URL: Documentation, https://jiby.tech/mass-driver
Project-URL: Repository, https://github.com/OverkillGuy/mass-driver
